{
	"info": {
		"_postman_id": "ad28c4e7-05e4-4f01-bef5-b7c18960219b",
		"name": "mini bank api",
		"schema": "https://schema.getpostman.com/json/collection/v2.1.0/collection.json"
	},
	"item": [
		{
			"name": "Users",
			"item": [
				{
					"name": "POST User",
					"request": {
						"auth": {
							"type": "noauth"
						},
						"method": "POST",
						"header": [
							{
								"warning": "This is a duplicate header and will be overridden by the Authorization header generated by Postman.",
								"key": "Authorization",
								"value": "aW9zX2FwcDpyYW5kb21fdG9rZW5fdHJ1c3RfbWU=",
								"type": "text"
							},
							{
								"key": "Content-Type",
								"value": "application/json",
								"type": "text"
							}
						],
						"body": {
							"mode": "raw",
							"raw": "{\n\t\"name\": \"FooUser\",\n\t\"token\": \"FooBarToken\"\n}"
						},
						"url": {
							"raw": "localhost:3000/api/v1/users",
							"host": [
								"localhost"
							],
							"port": "3000",
							"path": [
								"api",
								"v1",
								"users"
							],
							"query": [
								{
									"key": "name",
									"value": "Foo",
									"disabled": true
								},
								{
									"key": "token",
									"value": "FooBar",
									"disabled": true
								}
							]
						},
						"description": "This request create a new user"
					},
					"response": []
				}
			],
			"protocolProfileBehavior": {}
		},
		{
			"name": "Accounts",
			"item": [
				{
					"name": "GET Index",
					"request": {
						"method": "GET",
						"header": [
							{
								"key": "Authorization",
								"value": "FooBarToken",
								"type": "text"
							},
							{
								"key": "Content-Type",
								"value": "application/json",
								"type": "text"
							}
						],
						"url": {
							"raw": "localhost:3000/api/v1/accounts",
							"host": [
								"localhost"
							],
							"port": "3000",
							"path": [
								"api",
								"v1",
								"accounts"
							]
						}
					},
					"response": []
				},
				{
					"name": "GET Account",
					"request": {
						"method": "GET",
						"header": [
							{
								"key": "Authorization",
								"type": "text",
								"value": "FooBarToken"
							},
							{
								"key": "Content-Type",
								"type": "text",
								"value": "application/json"
							}
						],
						"url": {
							"raw": "localhost:3000/api/v1/accounts/2",
							"host": [
								"localhost"
							],
							"port": "3000",
							"path": [
								"api",
								"v1",
								"accounts",
								"2"
							]
						}
					},
					"response": []
				},
				{
					"name": "GET ByReferrals",
					"request": {
						"method": "GET",
						"header": [
							{
								"key": "Authorization",
								"type": "text",
								"value": "FooBarToken"
							},
							{
								"key": "Content-Type",
								"type": "text",
								"value": "application/json"
							}
						],
						"url": {
							"raw": "localhost:3000/api/v1/accounts/by_referral_code/n90ejBeJ",
							"host": [
								"localhost"
							],
							"port": "3000",
							"path": [
								"api",
								"v1",
								"accounts",
								"by_referral_code",
								"n90ejBeJ"
							]
						}
					},
					"response": []
				},
				{
					"name": "POST User incomplete request",
					"request": {
						"method": "POST",
						"header": [
							{
								"key": "Authorization",
								"value": "FooBarToken",
								"type": "text"
							},
							{
								"key": "Content-Type",
								"value": "application/json",
								"type": "text"
							}
						],
						"body": {
							"mode": "raw",
							"raw": "{\n\t\"cpf\": \"010101\"\n}"
						},
						"url": {
							"raw": "localhost:3000/api/v1/accounts",
							"host": [
								"localhost"
							],
							"port": "3000",
							"path": [
								"api",
								"v1",
								"accounts"
							]
						}
					},
					"response": []
				},
				{
					"name": "POST User complete request",
					"request": {
						"method": "POST",
						"header": [
							{
								"key": "Authorization",
								"type": "text",
								"value": "FooBarToken"
							},
							{
								"key": "Content-Type",
								"type": "text",
								"value": "application/json"
							}
						],
						"body": {
							"mode": "raw",
							"raw": "{\n\t\"cpf\": \"010101\",\n    \"email\":  \"fake@email.com\",\n    \"birth_date\": \"16/03/1993\",\n    \"gender\": \"Male\",\n    \"city\": \"São Paulo\",\n    \"state\": \"São Paulo\",\n    \"country\": \"Brazil\",\n    \"referral_code\": \"12345678\",\n    \"name\": \"Jhon Doe\"\n}"
						},
						"url": {
							"raw": "localhost:3000/api/v1/accounts",
							"host": [
								"localhost"
							],
							"port": "3000",
							"path": [
								"api",
								"v1",
								"accounts"
							]
						}
					},
					"response": []
				},
				{
					"name": "POST User New related account",
					"request": {
						"method": "POST",
						"header": [
							{
								"key": "Authorization",
								"value": "FooBarToken",
								"type": "text"
							},
							{
								"key": "Content-Type",
								"value": "application/json",
								"type": "text"
							}
						],
						"body": {
							"mode": "raw",
							"raw": "{\n\t\"cpf\": \"020202\",\n    \"email\":  \"another_fake@email.com\",\n    \"birth_date\": \"16/03/2003\",\n    \"gender\": \"Female\",\n    \"city\": \"Itapecerica da Serra\",\n    \"state\": \"São Paulo\",\n    \"country\": \"Brazil\",\n    \"referral_code\": \"n90ejBeJ\",\n    \"name\": \"Mary Doe\"\n}"
						},
						"url": {
							"raw": "localhost:3000/api/v1/accounts",
							"host": [
								"localhost"
							],
							"port": "3000",
							"path": [
								"api",
								"v1",
								"accounts"
							]
						}
					},
					"response": []
				}
			],
			"protocolProfileBehavior": {}
		}
	],
	"protocolProfileBehavior": {}
}